aiomigrate/__init__.py
aiomigrate/run.py
aiomigrate-0.0.1.dist-info/LICENSE
aiomigrate-0.0.1.dist-info/METADATA
aiomigrate-0.0.1.dist-info/WHEEL
aiomigrate-0.0.1.dist-info/entry_points.txt
aiomigrate-0.0.1.dist-info/top_level.txt
aiomigrate-0.0.1.dist-info/zip-safe
aiomigrate-0.0.1.dist-info/RECORD
